django_wechat_member-0.3.5.dist-info/DESCRIPTION.rst
django_wechat_member-0.3.5.dist-info/METADATA
django_wechat_member-0.3.5.dist-info/RECORD
django_wechat_member-0.3.5.dist-info/WHEEL
django_wechat_member-0.3.5.dist-info/metadata.json
django_wechat_member-0.3.5.dist-info/top_level.txt
wechat_member/__init__.py
wechat_member/admin.py
wechat_member/api.py
wechat_member/apps.py
wechat_member/models.py
wechat_member/tests.py
wechat_member/urls.py
wechat_member/views.py
wechat_member/locale/zh_Hans/LC_MESSAGES/django.mo
wechat_member/locale/zh_Hans/LC_MESSAGES/django.po
